{"nodes": [{"id": "archive_e17", "label": "E17 (archived, superseded) -- Adoption-First Docs Rewrite (ADR-0025)", "file_type": "document", "source_file": "docs/plans/archive/E17.md", "source_location": null, "source_url": null, "captured_at": null, "author": null, "contributor": null}, {"id": "adr_0025", "label": "ADR-0025 -- Adoption-First Docs Lead Order", "file_type": "document", "source_file": "docs/plans/archive/E17.md", "source_location": null, "source_url": null, "captured_at": null, "author": null, "contributor": null}], "edges": [{"source": "archive_e17", "target": "adr_0025", "relation": "references", "confidence": "EXTRACTED", "confidence_score": 1.0, "source_file": "docs/plans/archive/E17.md", "source_location": null, "weight": 1.0}], "hyperedges": []}