{"nodes": [{"id": "doc_kazi_context", "label": ".kazi/context.md orientation pack", "file_type": "document", "source_file": ".kazi/context.md", "source_location": null, "source_url": null, "captured_at": null, "author": null, "contributor": null}, {"id": "adr_0010", "label": "ADR-0010: context injection re-exploration mitigation", "file_type": "document", "source_file": ".kazi/context.md", "source_location": null, "source_url": null, "captured_at": null, "author": null, "contributor": null}], "edges": [{"source": "doc_kazi_context", "target": "adr_0010", "relation": "references", "confidence": "EXTRACTED", "confidence_score": 1.0, "source_file": ".kazi/context.md", "source_location": null, "weight": 1.0}], "hyperedges": []}