{"nodes": [{"id": "doc_pool_verification_gate_md", "label": "docs/pool-verification-gate.md", "file_type": "document", "source_file": "docs/pool-verification-gate.md", "source_location": null, "source_url": null, "captured_at": null, "author": null, "contributor": null}, {"id": "pvg_doc", "label": "Pool Verification Gate (L1)", "file_type": "document", "source_file": "docs/pool-verification-gate.md", "source_location": null, "source_url": null, "captured_at": null, "author": null, "contributor": null}, {"id": "pvg_rationale", "label": "Why a gate (rationale)", "file_type": "document", "source_file": "docs/pool-verification-gate.md", "source_location": null, "source_url": null, "captured_at": null, "author": null, "contributor": null}, {"id": "pvg_kazi_plan_predicates", "label": "kazi plan --json --predicates", "file_type": "code", "source_file": "docs/pool-verification-gate.md", "source_location": null, "source_url": null, "captured_at": null, "author": null, "contributor": null}, {"id": "pvg_kazi_approve", "label": "kazi approve --json", "file_type": "code", "source_file": "docs/pool-verification-gate.md", "source_location": null, "source_url": null, "captured_at": null, "author": null, "contributor": null}, {"id": "pvg_kazi_apply_json", "label": "kazi apply --json (the gate run)", "file_type": "code", "source_file": "docs/pool-verification-gate.md", "source_location": null, "source_url": null, "captured_at": null, "author": null, "contributor": null}], "edges": [{"source": "pvg_rationale", "target": "pvg_doc", "relation": "rationale_for", "confidence": "EXTRACTED", "confidence_score": 1.0, "source_file": "docs/pool-verification-gate.md", "source_location": null, "weight": 1.0}, {"source": "pvg_doc", "target": "adr0026", "relation": "references", "confidence": "EXTRACTED", "confidence_score": 1.0, "source_file": "docs/pool-verification-gate.md", "source_location": null, "weight": 1.0}, {"source": "pvg_doc", "target": "pvg_acc_bridge_doc", "relation": "references", "confidence": "EXTRACTED", "confidence_score": 1.0, "source_file": "docs/pool-verification-gate.md", "source_location": null, "weight": 1.0}, {"source": "pvg_doc", "target": "pvg_orchestrator_recipe_doc", "relation": "references", "confidence": "EXTRACTED", "confidence_score": 1.0, "source_file": "docs/pool-verification-gate.md", "source_location": null, "weight": 1.0}, {"source": "pvg_doc", "target": "pvg_run_result_schema", "relation": "references", "confidence": "EXTRACTED", "confidence_score": 1.0, "source_file": "docs/pool-verification-gate.md", "source_location": null, "weight": 1.0}, {"source": "pvg_acc_bridge", "target": "pvg_kazi_plan_predicates", "relation": "calls", "confidence": "EXTRACTED", "confidence_score": 1.0, "source_file": "docs/pool-verification-gate.md", "source_location": null, "weight": 1.0}, {"source": "pvg_kazi_plan_predicates", "target": "pvg_kazi_approve", "relation": "calls", "confidence": "EXTRACTED", "confidence_score": 1.0, "source_file": "docs/pool-verification-gate.md", "source_location": null, "weight": 1.0}, {"source": "pvg_kazi_approve", "target": "pvg_kazi_apply_json", "relation": "calls", "confidence": "EXTRACTED", "confidence_score": 1.0, "source_file": "docs/pool-verification-gate.md", "source_location": null, "weight": 1.0}, {"source": "pvg_kazi_apply_json", "target": "pvg_gate_decide", "relation": "calls", "confidence": "EXTRACTED", "confidence_score": 1.0, "source_file": "docs/pool-verification-gate.md", "source_location": null, "weight": 1.0}, {"source": "pvg_gate_decide", "target": "pvg_doc", "relation": "implements", "confidence": "EXTRACTED", "confidence_score": 1.0, "source_file": "docs/pool-verification-gate.md", "source_location": null, "weight": 1.0}, {"source": "pvg_doc", "target": "tiering_signals_doc", "relation": "semantically_similar_to", "confidence": "INFERRED", "confidence_score": 0.72, "source_file": "docs/pool-verification-gate.md", "source_location": null, "weight": 1.0}], "hyperedges": [{"id": "pool_verification_gate_pipeline", "label": "acc-bridge -> plan -> approve -> apply -> gate.decide pipeline", "nodes": ["pvg_acc_bridge", "pvg_kazi_plan_predicates", "pvg_kazi_approve", "pvg_kazi_apply_json", "pvg_gate_decide"], "relation": "participate_in", "confidence": "EXTRACTED", "confidence_score": 0.95, "source_file": "docs/pool-verification-gate.md"}]}