{"nodes": [{"id": "adr0041_envelope_v2", "label": "Predicate envelope v2 (pass/score/prior_score/direction/evidence)", "file_type": "document", "source_file": "docs/adr/0041-predicate-envelope-v2-score-evidence-ratchet.md", "source_location": null, "source_url": null, "captured_at": null, "author": null, "contributor": null}, {"id": "adr0041_score_direction", "label": "score + direction (higher_better/lower_better) progress signal", "file_type": "document", "source_file": "docs/adr/0041-predicate-envelope-v2-score-evidence-ratchet.md", "source_location": null, "source_url": null, "captured_at": null, "author": null, "contributor": null}, {"id": "adr0041_evidence_envelope", "label": "Standard evidence item envelope (LSP-Diagnostic-shaped)", "file_type": "document", "source_file": "docs/adr/0041-predicate-envelope-v2-score-evidence-ratchet.md", "source_location": null, "source_url": null, "captured_at": null, "author": null, "contributor": null}, {"id": "adr0041_ratchet_mode", "label": "ratchet predicate mode (signal vs baseline)", "file_type": "document", "source_file": "docs/adr/0041-predicate-envelope-v2-score-evidence-ratchet.md", "source_location": null, "source_url": null, "captured_at": null, "author": null, "contributor": null}, {"id": "adr0041_sparse_reward_rationale", "label": "Rationale: sparse-vs-dense reward (Ng/Harada/Russell, HER, SWE-bench Fix Rate)", "file_type": "document", "source_file": "docs/adr/0041-predicate-envelope-v2-score-evidence-ratchet.md", "source_location": null, "source_url": null, "captured_at": null, "author": null, "contributor": null}], "edges": [{"source": "adr0041_sparse_reward_rationale", "target": "adr0041_score_direction", "relation": "rationale_for", "confidence": "EXTRACTED", "confidence_score": 1.0, "source_file": "docs/adr/0041-predicate-envelope-v2-score-evidence-ratchet.md", "source_location": null, "weight": 1.0}, {"source": "adr0041_envelope_v2", "target": "adr0041_score_direction", "relation": "implements", "confidence": "EXTRACTED", "confidence_score": 1.0, "source_file": "docs/adr/0041-predicate-envelope-v2-score-evidence-ratchet.md", "source_location": null, "weight": 1.0}, {"source": "adr0041_envelope_v2", "target": "adr0041_evidence_envelope", "relation": "implements", "confidence": "EXTRACTED", "confidence_score": 1.0, "source_file": "docs/adr/0041-predicate-envelope-v2-score-evidence-ratchet.md", "source_location": null, "weight": 1.0}, {"source": "adr0041_envelope_v2", "target": "adr0041_ratchet_mode", "relation": "implements", "confidence": "EXTRACTED", "confidence_score": 1.0, "source_file": "docs/adr/0041-predicate-envelope-v2-score-evidence-ratchet.md", "source_location": null, "weight": 1.0}, {"source": "adr0041_evidence_envelope", "target": "adr0040_evidence_extraction", "relation": "shares_data_with", "confidence": "EXTRACTED", "confidence_score": 1.0, "source_file": "docs/adr/0041-predicate-envelope-v2-score-evidence-ratchet.md", "source_location": null, "weight": 1.0}, {"source": "adr0041_envelope_v2", "target": "adr0002_goals_as_predicates", "relation": "references", "confidence": "EXTRACTED", "confidence_score": 1.0, "source_file": "docs/adr/0041-predicate-envelope-v2-score-evidence-ratchet.md", "source_location": null, "weight": 1.0}], "hyperedges": []}